lap_task1/__init__.py
lap_task1/eval.py
lap_task1/files.py
lap_task1-0.1.1.dist-info/entry_points.txt
lap_task1-0.1.1.dist-info/LICENSE
lap_task1-0.1.1.dist-info/WHEEL
lap_task1-0.1.1.dist-info/METADATA
lap_task1-0.1.1.dist-info/RECORD
