Metadata-Version: 2.3
Name: lap-task1
Version: 0.1.1
Summary: Evaluation tool for the Listener Acoustic Personalisation challenge
Author-email: Johan Pauwels <j.pauwels@qmul.ac.uk>
Requires-Python: >=3.9
Classifier: Programming Language :: Python :: 3
Classifier: License :: OSI Approved :: MIT License
Classifier: Operating System :: OS Independent
Requires-Dist: hartufo >=0.6.5
Requires-Dist: scikit-learn >=1.4
Project-URL: Home, https://github.com/jpauwels/lap-task1
Project-URL: Issues, https://github.com/jpauwels/lap-task1/issues
